LICENSE
MANIFEST.in
README.md
setup.cfg
setup.py
versioneer.py
mapsci/.DS_Store
mapsci/__init__.py
mapsci/_version.py
mapsci/multipole_mie_combining_rules.py
mapsci/quick_plots.py
mapsci.egg-info/PKG-INFO
mapsci.egg-info/SOURCES.txt
mapsci.egg-info/dependency_links.txt
mapsci.egg-info/requires.txt
mapsci.egg-info/top_level.txt
mapsci/data/README.md
mapsci/data/look_and_say.dat
mapsci/examples/CO2_CH3_fit.py
mapsci/examples/.ipynb_checkpoints/mapsci_example-checkpoint.ipynb
mapsci/tests/__init__.py
mapsci/tests/test_mapsci.py