Metadata-Version: 2.1
Name: mapsci
Version: 0.0.2
Summary: UNKNOWN
Home-page: UNKNOWN
Author: Jennifer A Clark
Author-email: jennifer.clark@gnarlyoak.com
License: BSD-3-Clause
Platform: UNKNOWN
Provides-Extra: extra
